sinkove/__init__.py
sinkove/__main__.py
sinkove-0.0.2.dist-info/METADATA
sinkove-0.0.2.dist-info/WHEEL
sinkove-0.0.2.dist-info/top_level.txt
sinkove-0.0.2.dist-info/RECORD
